{
  "報告者情報": {
    "名前": "リサ",
    "年齢": null,
    "職種": null,
    "勤続年数": null
  },
  "インシデントの概要": {
    "概要": "福井健太氏が倉庫内での積荷作業中にヒヤリハットまたは事故に遭遇したことの報告。リフターの位置に気づかずバランスを崩しそうになった。インタビュアーは福井健太氏に自己紹介とインタビューの目的を説明し、自己紹介を求めた。リサさんが報告を行った。"
  },
  "インシデント発生時の状況": {
    "当人_L": {
      "行動": "リフターの位置に気づかず、バランスを崩しそうになった。",
      "認知状態": "リフターの中段の位置を忘れていた。",
      "身体状態": "疲労を感じていた可能性あり。"
    },
    "周囲の人_L": {
      "その他": "同僚と少し話していた。"
    }
  },
  "事象に至るまでの経緯": "2023年10月1日16時30分頃、倉庫内での積荷作業中。荷物を積み終えた後、次の仕事について考え、同僚と会話していた。",
  "背後要因": {
    "組織": null
  },
  "普段と違った点": "リフターの位置確認を怠ったこと。",
  "原因": [
    "疲労",
    "他事への注意散漫"
  ],
  "類似事象": [],
  "対策": [
    "休憩時間の確保",
    "リフター使用時の注意喚起の徹底"
  ]
}