{
  "報告者情報": {
    "性別": "不明",
    "職種": "不明",
    "会社": "不明"
  },
  "インシデントの概要": {
    "概要": "ヒヤリハット報告に基づき、今回のインシデントから得られた教訓と、今後の安全対策についてまとめました。具体的なインシデントの内容は不明ですが、報告者の経験共有と再発防止への意識が確認されました。"
  },
  "インシデント発生時の状況": {
    "当人_L": {
      "行動": "左手で段ボールを強く押さえ込む",
      "身体状態": "不明"
    },
    "周囲の人_L": {
      "その他": "同僚と会話"
    }
  },
  "事象に至るまでの経緯": "複数の要因が複合的に作用し、ヒヤリハットが発生しました。具体的には、以下の要素が挙げられます。",
  "背後要因": {
    "組織": {
      "情報共有_情報開示": "不明",
      "リスクマネジメント": "不明",
      "コミュニケーション": "上司からの作業の急かし"
    }
  },
  "普段と違った点": "カッターナイフの刃の切れ味が鋭利すぎた",
  "原因": [
    "カッターナイフの刃の切れ味が鋭利すぎた",
    "作業時の姿勢（左手で段ボールを強く押さえ込む）",
    "作業中の注意散漫（手元を見ずに同僚と会話）",
    "上司からの作業の急かし",
    "焦りによる危険回避の欠如"
  ],
  "類似事象": [
    "作業完了への焦りが危険な行動につながる可能性",
    "焦りによる危険回避の欠如"
  ],
  "対策": [
    "作業前の安全確認",
    "カッターナイフの取り扱い方法の再確認",
    "集中作業の徹底",
    "指示への適切な対応",
    "周囲との協力体制の構築",
    "「焦らない」「安全第一」の意識徹底",
    "経験共有による安全意識の向上"
  ]
}