{
  "報告者情報": {
    "会社": "不明",
    "勤続年数": null
  },
  "インシデントの概要": {
    "日付": "不明",
    "場所": "物流倉庫",
    "概要": "原材料の段ボールを開梱する作業中、カッターナイフの使用中に刃が指に当たった。怪我は指先の擦り傷程度で、出血はほとんどなかった。"
  },
  "インシデント発生時の状況": {
    "物理環境_E": {
      "温度": "不明",
      "湿度": "不明",
      "明るさ": "不明",
      "その他": "安全上の危険物はなし"
    },
    "周囲の人_L": {
      "同僚": "同僚との会話に気取られ、注意散漫になっていた。",
      "上司": "上司からの急かしがあった。"
    }
  },
  "事象に至るまでの経緯": "新しいカッターナイフに交換されたばかりで切れ味が鋭かったため、通常より早く作業しようとした。作業前の刃の状態確認など、安全確認が不十分だった可能性がある。",
  "背後要因": {
    "組織": {
      "リスクマネジメント": "安全確認の習慣化ができていない可能性がある。",
      "コミュニケーション": "上司からの急かしが、作業スピードを上げるプレッシャーを与えた。"
    }
  },
  "普段と違った点": "新しいカッターナイフの切れ味を過信していたこと。",
  "原因": [
    "作業スピードの上げすぎ",
    "注意散漫",
    "指の位置への意識不足",
    "作業前の確認不足",
    "集中力の欠如",
    "安全確認の習慣化の欠如"
  ],
  "類似事象": [
    "過去に同様のヒヤリハット事例がないか確認が必要。"
  ],
  "対策": [
    "作業前の確認ルール徹底",
    "集中できる環境整備",
    "安全確認の習慣化"
  ]
}